edx_token_utils-0.3.1.dist-info/licenses/LICENSE.txt
token_utils/__init__.py
token_utils/api.py
token_utils/apps.py
token_utils/models.py
token_utils/sign.py
token_utils/unpack.py
token_utils/urls.py
token_utils/templates/token_utils/base.html
token_utils/tests/test_sign.py
token_utils/tests/test_unpack.py
edx_token_utils-0.3.1.dist-info/METADATA
edx_token_utils-0.3.1.dist-info/WHEEL
edx_token_utils-0.3.1.dist-info/top_level.txt
edx_token_utils-0.3.1.dist-info/RECORD
