Metadata-Version: 2.4
Name: edx-token-utils
Version: 0.3.1
Summary: App for the creation, signing, and decoding of various access tokens
Home-page: https://github.com/edx/token-utils
Author: edX
Author-email: oscm@edx.org
License: AGPL 3.0
Keywords: Python edx
Classifier: Development Status :: 3 - Alpha
Classifier: Framework :: Django
Classifier: Framework :: Django :: 3.2
Classifier: Intended Audience :: Developers
Classifier: License :: OSI Approved :: GNU Affero General Public License v3 or later (AGPLv3+)
Classifier: Natural Language :: English
Classifier: Programming Language :: Python :: 3
Classifier: Programming Language :: Python :: 3.8
Requires-Python: >=3.8
License-File: LICENSE.txt
Requires-Dist: Django
Requires-Dist: cryptography
Requires-Dist: pyjwt
Dynamic: author
Dynamic: author-email
Dynamic: classifier
Dynamic: description
Dynamic: home-page
Dynamic: keywords
Dynamic: license
Dynamic: license-file
Dynamic: requires-dist
Dynamic: requires-python
Dynamic: summary
